Workbook
Name aportes: Sheet!$C$10
Name qtd_anos: Sheet!$C$11
Name rendimento_carteira: Sheet!$C$6
Name salario: Sheet!$C$5
Name sugestao_investimento: Sheet!$C$7
Name taxa_mensal: Sheet!$C$12

Sheet Sheet
B4: Configurações
B5: Salário | C5: 3100
B6: Rendimento Carteira | C6: 0.01
B7: Sugestão de Investimento | C7: =C5*30% -> 930
B9: Investimento Mensal
B10: Quanto investir por mês? | C10: 500
B11: Por Quantos Anos ? | C11: 10
B12: Taxa de Rendimento Mensal? | C12: 0.0089
B13: Patrimonio acumulado ? | C13: =FV(C12,C11*12,C10*-1) -> 106507.9
B14: Dividendos Mensais ? | C14: =C13*1% -> 1065.079
B17: Cenários | C17: Patrimonio | D17: Dividendos
A18: 2 | B18: Quanto em 2 anos? | C18: =FV($C$12,$A18*12,$C$10*-1) -> 13312.243 | D18: =C18*$C$6 -> 133.12243
A19: 5 | B19: Quanto em 5 anos? | C19: =FV($C$12,$A19*12,$C$10*-1) -> 39422.3 | D19: =C19*$C$6 -> 394.223
A20: 10 | B20: Quanto em 10 anos? | C20: =FV($C$12,$A20*12,$C$10*-1) -> 106507.9 | D20: =C20*$C$6 -> 1065.079
A21: 20 | B21: Quanto em 20 anos? | C21: =FV($C$12,$A21*12,$C$10*-1) -> 414937.78 | D21: =C21*$C$6 -> 4149.3778
A22: 30 | B22: Quanto em 30 anos? | C22: =FV($C$12,$A22*12,$C$10*-1) -> 1308101.5 | D22: =C22*$C$6 -> 13081.015
B25: Perfil | C25: Moderado
B26: Valor a ser investido por mês | C26: =sugestao_investimento -> 930
B28: Tipo de FIIs | C28: Percentual Sugerido | D28: Valores
B29: Papel | C29: =VLOOKUP($C$25&"-"&B29,Sheet_Base!$A:$D,4,FALSE) -> 0.32 | D29: =C29*$C$26 -> 297.6
B30: Tijolo | C30: =VLOOKUP($C$25&"-"&B30,Sheet_Base!$A:$D,4,FALSE) -> 0.35 | D30: =C30*$C$26 -> 325.5
B31: Hidridos | C31: =VLOOKUP($C$25&"-"&B31,Sheet_Base!$A:$D,4,FALSE) -> 0.08 | D31: =C31*$C$26 -> 74.4
B32: FOFs | C32: =VLOOKUP($C$25&"-"&B32,Sheet_Base!$A:$D,4,FALSE) -> 0.05 | D32: =C32*$C$26 -> 46.5
B33: Desenvolvimentos | C33: =VLOOKUP($C$25&"-"&B33,Sheet_Base!$A:$D,4,FALSE) -> 0.1 | D33: =C33*$C$26 -> 93
B34: Hotelarias | C34: =VLOOKUP($C$25&"-"&B34,Sheet_Base!$A:$D,4,FALSE) -> 0.1 | D34: =C34*$C$26 -> 93
D35: =SUM(D29:D34) -> 930

Sheet Sheet_Base
A3: Chave | B3: Perfil | C3: Tipo de FIIs | D3: %
A4: =B4&"-"&C4 -> Conservador -Papel | B4: Conservador | C4: Papel | D4: 0.3
A5: =B5&"-"&C5 -> Conservador -Tijolo | B5: Conservador | C5: Tijolo | D5: 0.5
A6: =B6&"-"&C6 -> Conservador -Hidridos | B6: Conservador | C6: Hidridos | D6: 0.1
A7: =B7&"-"&C7 -> Conservador -FOFs | B7: Conservador | C7: FOFs | D7: 0.1
A8: =B8&"-"&C8 -> Conservador -Desenvolvimentos | B8: Conservador | C8: Desenvolvimentos | D8: 0
A9: =B9&"-"&C9 -> Conservador -Hotelarias | B9: Conservador | C9: Hotelarias | D9: 0
A10: =B10&"-"&C10 -> Moderado-Papel | B10: Moderado | C10: Papel | D10: 0.32
A11: =B11&"-"&C11 -> Moderado-Tijolo | B11: Moderado | C11: Tijolo | D11: 0.35
A12: =B12&"-"&C12 -> Moderado-Hidridos | B12: Moderado | C12: Hidridos | D12: 0.08
A13: =B13&"-"&C13 -> Moderado-FOFs | B13: Moderado | C13: FOFs | D13: 0.05
A14: =B14&"-"&C14 -> Moderado-Desenvolvimentos | B14: Moderado | C14: Desenvolvimentos | D14: 0.1
A15: =B15&"-"&C15 -> Moderado-Hotelarias | B15: Moderado | C15: Hotelarias | D15: 0.1
... A21: =B21&"-"&C21 -> Agressivo-Hotelarias | B21: Agressivo | C21: Hotelarias | D21: 0.1
